rustic_ai/langchain/__init__.py
rustic_ai/langchain/agent_ext/__init__.py
rustic_ai/langchain/agent_ext/embeddings/__init__.py
rustic_ai/langchain/agent_ext/embeddings/openai.py
rustic_ai/langchain/agent_ext/text_splitter/__init__.py
rustic_ai/langchain/agent_ext/text_splitter/character_splitter.py
rustic_ai/langchain/agent_ext/text_splitter/recursive_splitter.py
rustic_ai/langchain/utils/__init__.py
rustic_ai/langchain/utils/doc_utils.py
rustic_ai/langchain/utils/index_utils.py
rusticai_langchain-1.0.0.dist-info/METADATA
rusticai_langchain-1.0.0.dist-info/WHEEL
rusticai_langchain-1.0.0.dist-info/RECORD
